README.md
setup.py
fermi_repoman.egg-info/PKG-INFO
fermi_repoman.egg-info/SOURCES.txt
fermi_repoman.egg-info/dependency_links.txt
fermi_repoman.egg-info/entry_points.txt
fermi_repoman.egg-info/requires.txt
fermi_repoman.egg-info/top_level.txt
fermi_repoman.egg-info/zip-safe
repoman/__init__.py
repoman/cli.py
repoman/error.py
repoman/manifest.py
repoman/package.py
repoman/release.py
repoman/tag.py
repoman/workspace.py