Metadata-Version: 1.1
Name: fermi-repoman
Version: 0.2.3
Summary: A collection of utilities for managing individual software packages for the Fermi Gamma-Ray Space telescope
Home-page: http://github.com/fermi-lat/repoman
Author: Brian Van Klaveren
Author-email: bvan@slac.stanford.edu
License: Modified BSD
Platform: UNKNOWN
Classifier: Intended Audience :: Science/Research
Classifier: Programming Language :: Python
Classifier: Programming Language :: Python :: 2
Classifier: Programming Language :: Python :: 2.7
Classifier: Programming Language :: Python :: 3
Classifier: Programming Language :: Python :: 3.5
